calculator/__init__.py
calculator/calculator.py
calculator/test_calculator.py
final_calculator_martin_macak-0.0.1.dist-info/LICENSE.txt
final_calculator_martin_macak-0.0.1.dist-info/METADATA
final_calculator_martin_macak-0.0.1.dist-info/WHEEL
final_calculator_martin_macak-0.0.1.dist-info/top_level.txt
final_calculator_martin_macak-0.0.1.dist-info/RECORD
