Metadata-Version: 2.1
Name: final-calculator-martin-macak
Version: 0.0.1
Summary: Calculator package for Turing College
Home-page: https://github.com/electroqwerty
Author: Martin Macak
Author-email: martinmacak@protonmail.com
Project-URL: Bug Tracker, https://github.com/electroqwerty
Classifier: Programming Language :: Python :: 3
Classifier: License :: OSI Approved :: MIT License
Classifier: Operating System :: OS Independent
Requires-Python: >=3.6
License-File: LICENSE.txt
